norby/__init__.py
norby/__main__.py
norby/utils.py
norby/version.py
norby-0.0.1.dev0.dist-info/LICENSE
norby-0.0.1.dev0.dist-info/METADATA
norby-0.0.1.dev0.dist-info/WHEEL
norby-0.0.1.dev0.dist-info/entry_points.txt
norby-0.0.1.dev0.dist-info/top_level.txt
norby-0.0.1.dev0.dist-info/RECORD
